README.rst
setup.py
codetools/__init__.py
codetools/_version.py
codetools.egg-info/PKG-INFO
codetools.egg-info/SOURCES.txt
codetools.egg-info/dependency_links.txt
codetools.egg-info/not-zip-safe
codetools.egg-info/requires.txt
codetools.egg-info/top_level.txt
codetools/blocks/__init__.py
codetools/blocks/analysis.py
codetools/blocks/api.py
codetools/blocks/block.py
codetools/blocks/compiler_unparse.py
codetools/blocks/decorators.py
codetools/blocks/namespace_tools.py
codetools/blocks/parser_.py
codetools/blocks/rename.py
codetools/blocks/ast_25/__init__.py
codetools/blocks/ast_25/api.py
codetools/blocks/ast_25/ast.py
codetools/blocks/ast_25/parser.py
codetools/blocks/ast_25/unparse_.py
codetools/blocks/compiler_/__init__.py
codetools/blocks/compiler_/api.py
codetools/blocks/compiler_/compiler_.py
codetools/blocks/compiler_/ast/__init__.py
codetools/blocks/compiler_/ast/api.py
codetools/blocks/compiler_/ast/ast.py
codetools/blocks/compiler_/ast/deep_equality.py
codetools/blocks/compiler_/ast/extract_children_trees.py
codetools/blocks/compiler_/ast/get_children_tree.py
codetools/blocks/compiler_/tests/__init__.py
codetools/blocks/tests/__init__.py
codetools/blocks/tests/decorators_test.py
codetools/blocks/tests/error_continue_test.py
codetools/blocks/tests/test_block.py
codetools/blocks/tests/test_namespace_tools.py
codetools/blocks2/__init__.py
codetools/blocks2/analysis.py
codetools/blocks2/block.py
codetools/blocks2/block_transformer.py
codetools/blocks2/tests/__init__.py
codetools/blocks2/tests/test_block.py
codetools/contexts/__init__.py
codetools/contexts/adapted_data_context.py
codetools/contexts/api.py
codetools/contexts/context_function.py
codetools/contexts/data_context.py
codetools/contexts/function_filter_context.py
codetools/contexts/geo_context.py
codetools/contexts/hdf5_context.py
codetools/contexts/i_adapted_data_context.py
codetools/contexts/i_context.py
codetools/contexts/items_modified_event.py
codetools/contexts/iterable_adapted_data_context.py
codetools/contexts/multi_context.py
codetools/contexts/name_filter_context.py
codetools/contexts/traitslike_context_wrapper.py
codetools/contexts/utils.py
codetools/contexts/with_mask.py
