Metadata-Version: 1.2
Name: codetools
Version: 4.3.0
Summary: code analysis and execution tools
Home-page: https://github.com/enthought/codetools
Author: Enthought, Inc.
Author-email: info@enthought.com
Maintainer: ETS Developers
Maintainer-email: enthought-dev@enthought.com
License: BSD
Download-URL: http://www.enthought.com/repo/ets/codetools-4.3.0.tar.gz
Platform: Windows
Platform: Linux
Platform: Mac OS-X
Platform: Unix
Platform: Solaris
Classifier: Development Status :: 5 - Production/Stable
Classifier: Intended Audience :: Developers
Classifier: Intended Audience :: Science/Research
Classifier: License :: OSI Approved :: BSD License
Classifier: Operating System :: MacOS
Classifier: Operating System :: Microsoft :: Windows
Classifier: Operating System :: OS Independent
Classifier: Operating System :: POSIX
Classifier: Operating System :: Unix
Classifier: Programming Language :: Python
Classifier: Topic :: Scientific/Engineering
Classifier: Topic :: Software Development
Classifier: Topic :: Software Development :: Libraries
